Metadata-Version: 2.1
Name: quickfix-ch
Version: 0.0.16
Summary: FIX (Financial Information eXchange) protocol implementation
Home-page: http://www.quickfixengine.org
Download-URL: http://www.quickfixengine.org
Author: Javier (coinhako)
Author-email: javier.phon@coinhako.com
Maintainer: Javier (coinhako)
Maintainer-email: javier.phon@coinhako.com
License: The QuickFIX Software License, Version 1.0
License-File: LICENSE
